{"warnings":[{"file":"/Users/marc/Dropbox/projects/Marvel Heroes/Marvel Heroes/Model/Comic.swift","line":17,"symbol":"_title","symbol_kind":"source.lang.swift.decl.var.instance","warning":"undocumented"},{"file":"/Users/marc/Dropbox/projects/Marvel Heroes/Marvel Heroes/Model/Comic.swift","line":18,"symbol":"_comicId","symbol_kind":"source.lang.swift.decl.var.instance","warning":"undocumented"},{"file":"/Users/marc/Dropbox/projects/Marvel Heroes/Marvel Heroes/Model/Comic.swift","line":19,"symbol":"_thumbnailUrl","symbol_kind":"source.lang.swift.decl.var.instance","warning":"undocumented"},{"file":"/Users/marc/Dropbox/projects/Marvel Heroes/Marvel Heroes/Model/Comic.swift","line":21,"symbol":"init(title:comicId:thumbnailUrl:)","symbol_kind":"source.lang.swift.decl.function.method.instance","warning":"undocumented"},{"file":"/Users/marc/Dropbox/projects/Marvel Heroes/Marvel Heroes/Model/Comic.swift","line":27,"symbol":"title","symbol_kind":"source.lang.swift.decl.var.instance","warning":"undocumented"},{"file":"/Users/marc/Dropbox/projects/Marvel Heroes/Marvel Heroes/Model/Comic.swift","line":31,"symbol":"comicId","symbol_kind":"source.lang.swift.decl.var.instance","warning":"undocumented"},{"file":"/Users/marc/Dropbox/projects/Marvel Heroes/Marvel Heroes/Model/Comic.swift","line":36,"symbol":"thumbnailUrl","symbol_kind":"source.lang.swift.decl.var.instance","warning":"undocumented"},{"file":"/Users/marc/Dropbox/projects/Marvel Heroes/Marvel Heroes/Model/Comic.swift","line":43,"symbol":"description","symbol_kind":"source.lang.swift.decl.var.instance","warning":"undocumented"},{"file":"/Users/marc/Dropbox/projects/Marvel Heroes/Marvel Heroes/Controllers/SuggestionsViewController.swift","line":20,"symbol":"heroes","symbol_kind":"source.lang.swift.decl.var.instance","warning":"undocumented"},{"file":"/Users/marc/Dropbox/projects/Marvel Heroes/Marvel Heroes/Controllers/SuggestionsViewController.swift","line":21,"symbol":"selectedHero","symbol_kind":"source.lang.swift.decl.var.instance","warning":"undocumented"},{"file":"/Users/marc/Dropbox/projects/Marvel Heroes/Marvel Heroes/Controllers/SuggestionsViewController.swift","line":23,"symbol":"viewDidLoad()","symbol_kind":"source.lang.swift.decl.function.method.instance","warning":"undocumented"},{"file":"/Users/marc/Dropbox/projects/Marvel Heroes/Marvel Heroes/Controllers/SuggestionsViewController.swift","line":37,"symbol":"deinit","symbol_kind":"source.lang.swift.decl.function.method.instance","warning":"undocumented"},{"file":"/Users/marc/Dropbox/projects/Marvel Heroes/Marvel Heroes/Controllers/SuggestionsViewController.swift","line":42,"symbol":"numberOfSectionsInTableView(_:)","symbol_kind":"source.lang.swift.decl.function.method.instance","warning":"undocumented"},{"file":"/Users/marc/Dropbox/projects/Marvel Heroes/Marvel Heroes/Controllers/SuggestionsViewController.swift","line":46,"symbol":"tableView(_:numberOfRowsInSection:)","symbol_kind":"source.lang.swift.decl.function.method.instance","warning":"undocumented"},{"file":"/Users/marc/Dropbox/projects/Marvel Heroes/Marvel Heroes/Controllers/SuggestionsViewController.swift","line":50,"symbol":"tableView(_:cellForRowAtIndexPath:)","symbol_kind":"source.lang.swift.decl.function.method.instance","warning":"undocumented"},{"file":"/Users/marc/Dropbox/projects/Marvel Heroes/Marvel Heroes/Controllers/SuggestionsViewController.swift","line":59,"symbol":"tableView(_:didSelectRowAtIndexPath:)","symbol_kind":"source.lang.swift.decl.function.method.instance","warning":"undocumented"},{"file":"/Users/marc/Dropbox/projects/Marvel Heroes/Marvel Heroes/Views/ComicCell.swift","line":17,"symbol":"thumbImg","symbol_kind":"source.lang.swift.decl.var.instance","warning":"undocumented"},{"file":"/Users/marc/Dropbox/projects/Marvel Heroes/Marvel Heroes/Views/ComicCell.swift","line":18,"symbol":"nameLbl","symbol_kind":"source.lang.swift.decl.var.instance","warning":"undocumented"},{"file":"/Users/marc/Dropbox/projects/Marvel Heroes/Marvel Heroes/Views/ComicCell.swift","line":20,"symbol":"comic","symbol_kind":"source.lang.swift.decl.var.instance","warning":"undocumented"},{"file":"/Users/marc/Dropbox/projects/Marvel Heroes/Marvel Heroes/Views/ComicCell.swift","line":22,"symbol":"init(coder:)","symbol_kind":"source.lang.swift.decl.function.method.instance","warning":"undocumented"},{"file":"/Users/marc/Dropbox/projects/Marvel Heroes/Marvel Heroes/Views/ComicCell.swift","line":26,"symbol":"configureCell(_:)","symbol_kind":"source.lang.swift.decl.function.method.instance","warning":"undocumented"},{"file":"/Users/marc/Dropbox/projects/Marvel Heroes/Marvel Heroes/Services/parser.swift","line":20,"symbol":"_data","symbol_kind":"source.lang.swift.decl.var.instance","warning":"undocumented"},{"file":"/Users/marc/Dropbox/projects/Marvel Heroes/Marvel Heroes/Services/parser.swift","line":22,"symbol":"init(data:)","symbol_kind":"source.lang.swift.decl.function.method.instance","warning":"undocumented"},{"file":"/Users/marc/Dropbox/projects/Marvel Heroes/Marvel Heroes/Services/parser.swift","line":26,"symbol":"init()","symbol_kind":"source.lang.swift.decl.function.method.instance","warning":"undocumented"},{"file":"/Users/marc/Dropbox/projects/Marvel Heroes/Marvel Heroes/Services/parser.swift","line":30,"symbol":"parseJSON(_:)","symbol_kind":"source.lang.swift.decl.function.method.instance","warning":"undocumented"},{"file":"/Users/marc/Dropbox/projects/Marvel Heroes/Marvel Heroes/Services/parser.swift","line":35,"symbol":"parseHero()","symbol_kind":"source.lang.swift.decl.function.method.instance","warning":"undocumented"},{"file":"/Users/marc/Dropbox/projects/Marvel Heroes/Marvel Heroes/Services/parser.swift","line":64,"symbol":"parseComics()","symbol_kind":"source.lang.swift.decl.function.method.instance","warning":"undocumented"},{"file":"/Users/marc/Dropbox/projects/Marvel Heroes/Marvel Heroes/Views/HeroCell.swift","line":17,"symbol":"thumbImg","symbol_kind":"source.lang.swift.decl.var.instance","warning":"undocumented"},{"file":"/Users/marc/Dropbox/projects/Marvel Heroes/Marvel Heroes/Views/HeroCell.swift","line":18,"symbol":"nameLbl","symbol_kind":"source.lang.swift.decl.var.instance","warning":"undocumented"},{"file":"/Users/marc/Dropbox/projects/Marvel Heroes/Marvel Heroes/Views/HeroCell.swift","line":20,"symbol":"hero","symbol_kind":"source.lang.swift.decl.var.instance","warning":"undocumented"},{"file":"/Users/marc/Dropbox/projects/Marvel Heroes/Marvel Heroes/Views/HeroCell.swift","line":22,"symbol":"init(coder:)","symbol_kind":"source.lang.swift.decl.function.method.instance","warning":"undocumented"},{"file":"/Users/marc/Dropbox/projects/Marvel Heroes/Marvel Heroes/Views/HeroCell.swift","line":29,"symbol":"configureCell(_:)","symbol_kind":"source.lang.swift.decl.function.method.instance","warning":"undocumented"},{"file":"/Users/marc/Dropbox/projects/Marvel Heroes/Marvel Heroes/Services/apiClient.swift","line":18,"symbol":"persistencyManager","symbol_kind":"source.lang.swift.decl.var.instance","warning":"undocumented"},{"file":"/Users/marc/Dropbox/projects/Marvel Heroes/Marvel Heroes/Services/apiClient.swift","line":19,"symbol":"isOnline","symbol_kind":"source.lang.swift.decl.var.instance","warning":"undocumented"},{"file":"/Users/marc/Dropbox/projects/Marvel Heroes/Marvel Heroes/Services/apiClient.swift","line":20,"symbol":"parseManager","symbol_kind":"source.lang.swift.decl.var.instance","warning":"undocumented"},{"file":"/Users/marc/Dropbox/projects/Marvel Heroes/Marvel Heroes/Services/apiClient.swift","line":24,"symbol":"sharedInstance","symbol_kind":"source.lang.swift.decl.var.class","warning":"undocumented"},{"file":"/Users/marc/Dropbox/projects/Marvel Heroes/Marvel Heroes/Services/apiClient.swift","line":25,"symbol":"Singleton","symbol_kind":"source.lang.swift.decl.struct","warning":"undocumented"},{"file":"/Users/marc/Dropbox/projects/Marvel Heroes/Marvel Heroes/Services/apiClient.swift","line":26,"symbol":"instance","symbol_kind":"source.lang.swift.decl.var.static","warning":"undocumented"},{"file":"/Users/marc/Dropbox/projects/Marvel Heroes/Marvel Heroes/Services/apiClient.swift","line":31,"symbol":"init()","symbol_kind":"source.lang.swift.decl.function.method.instance","warning":"undocumented"},{"file":"/Users/marc/Dropbox/projects/Marvel Heroes/Marvel Heroes/Views/suggestionCell.swift","line":18,"symbol":"nameLabel","symbol_kind":"source.lang.swift.decl.var.instance","warning":"undocumented"},{"file":"/Users/marc/Dropbox/projects/Marvel Heroes/Marvel Heroes/Views/suggestionCell.swift","line":19,"symbol":"thumbImg","symbol_kind":"source.lang.swift.decl.var.instance","warning":"undocumented"},{"file":"/Users/marc/Dropbox/projects/Marvel Heroes/Marvel Heroes/Views/suggestionCell.swift","line":22,"symbol":"hero","symbol_kind":"source.lang.swift.decl.var.instance","warning":"undocumented"},{"file":"/Users/marc/Dropbox/projects/Marvel Heroes/Marvel Heroes/Views/suggestionCell.swift","line":24,"symbol":"awakeFromNib()","symbol_kind":"source.lang.swift.decl.function.method.instance","warning":"undocumented"},{"file":"/Users/marc/Dropbox/projects/Marvel Heroes/Marvel Heroes/Views/suggestionCell.swift","line":29,"symbol":"setSelected(_:animated:)","symbol_kind":"source.lang.swift.decl.function.method.instance","warning":"undocumented"},{"file":"/Users/marc/Dropbox/projects/Marvel Heroes/Marvel Heroes/Views/suggestionCell.swift","line":34,"symbol":"configureCell(_:)","symbol_kind":"source.lang.swift.decl.function.method.instance","warning":"undocumented"},{"file":"/Users/marc/Dropbox/projects/Marvel Heroes/Marvel Heroes/Views/HeroDetailVC.swift","line":20,"symbol":"image","symbol_kind":"source.lang.swift.decl.var.instance","warning":"undocumented"},{"file":"/Users/marc/Dropbox/projects/Marvel Heroes/Marvel Heroes/Views/HeroDetailVC.swift","line":21,"symbol":"avatarImage","symbol_kind":"source.lang.swift.decl.var.instance","warning":"undocumented"},{"file":"/Users/marc/Dropbox/projects/Marvel Heroes/Marvel Heroes/Views/HeroDetailVC.swift","line":22,"symbol":"nameLabel","symbol_kind":"source.lang.swift.decl.var.instance","warning":"undocumented"},{"file":"/Users/marc/Dropbox/projects/Marvel Heroes/Marvel Heroes/Views/HeroDetailVC.swift","line":23,"symbol":"detailDescriptionLabel","symbol_kind":"source.lang.swift.decl.var.instance","warning":"undocumented"},{"file":"/Users/marc/Dropbox/projects/Marvel Heroes/Marvel Heroes/Views/HeroDetailVC.swift","line":24,"symbol":"idLabel","symbol_kind":"source.lang.swift.decl.var.instance","warning":"undocumented"},{"file":"/Users/marc/Dropbox/projects/Marvel Heroes/Marvel Heroes/Views/HeroDetailVC.swift","line":25,"symbol":"collection","symbol_kind":"source.lang.swift.decl.var.instance","warning":"undocumented"},{"file":"/Users/marc/Dropbox/projects/Marvel Heroes/Marvel Heroes/Views/HeroDetailVC.swift","line":26,"symbol":"closeButton","symbol_kind":"source.lang.swift.decl.var.instance","warning":"undocumented"},{"file":"/Users/marc/Dropbox/projects/Marvel Heroes/Marvel Heroes/Views/HeroDetailVC.swift","line":28,"symbol":"comicsEmptyStateLabel","symbol_kind":"source.lang.swift.decl.var.instance","warning":"undocumented"},{"file":"/Users/marc/Dropbox/projects/Marvel Heroes/Marvel Heroes/Views/HeroDetailVC.swift","line":29,"symbol":"scrollView","symbol_kind":"source.lang.swift.decl.var.instance","warning":"undocumented"},{"file":"/Users/marc/Dropbox/projects/Marvel Heroes/Marvel Heroes/Views/HeroDetailVC.swift","line":31,"symbol":"blurImage","symbol_kind":"source.lang.swift.decl.var.instance","warning":"undocumented"},{"file":"/Users/marc/Dropbox/projects/Marvel Heroes/Marvel Heroes/Views/HeroDetailVC.swift","line":32,"symbol":"dismissButton(_:)","symbol_kind":"source.lang.swift.decl.function.method.instance","warning":"undocumented"},{"file":"/Users/marc/Dropbox/projects/Marvel Heroes/Marvel Heroes/Views/HeroDetailVC.swift","line":35,"symbol":"comicsActivityIndicator","symbol_kind":"source.lang.swift.decl.var.instance","warning":"undocumented"},{"file":"/Users/marc/Dropbox/projects/Marvel Heroes/Marvel Heroes/Views/HeroDetailVC.swift","line":37,"symbol":"hero","symbol_kind":"source.lang.swift.decl.var.instance","warning":"undocumented"},{"file":"/Users/marc/Dropbox/projects/Marvel Heroes/Marvel Heroes/Views/HeroDetailVC.swift","line":38,"symbol":"comics","symbol_kind":"source.lang.swift.decl.var.instance","warning":"undocumented"},{"file":"/Users/marc/Dropbox/projects/Marvel Heroes/Marvel Heroes/Views/HeroDetailVC.swift","line":39,"symbol":"comicOffset","symbol_kind":"source.lang.swift.decl.var.instance","warning":"undocumented"},{"file":"/Users/marc/Dropbox/projects/Marvel Heroes/Marvel Heroes/Views/HeroDetailVC.swift","line":40,"symbol":"blurView","symbol_kind":"source.lang.swift.decl.var.instance","warning":"undocumented"},{"file":"/Users/marc/Dropbox/projects/Marvel Heroes/Marvel Heroes/Views/HeroDetailVC.swift","line":41,"symbol":"presentedModally","symbol_kind":"source.lang.swift.decl.var.instance","warning":"undocumented"},{"file":"/Users/marc/Dropbox/projects/Marvel Heroes/Marvel Heroes/Views/HeroDetailVC.swift","line":43,"symbol":"viewDidLoad()","symbol_kind":"source.lang.swift.decl.function.method.instance","warning":"undocumented"},{"file":"/Users/marc/Dropbox/projects/Marvel Heroes/Marvel Heroes/Views/HeroDetailVC.swift","line":94,"symbol":"listenToNotifications()","symbol_kind":"source.lang.swift.decl.function.method.instance","warning":"undocumented"},{"file":"/Users/marc/Dropbox/projects/Marvel Heroes/Marvel Heroes/Views/HeroDetailVC.swift","line":109,"symbol":"deinit","symbol_kind":"source.lang.swift.decl.function.method.instance","warning":"undocumented"},{"file":"/Users/marc/Dropbox/projects/Marvel Heroes/Marvel Heroes/Views/HeroDetailVC.swift","line":114,"symbol":"scrollViewDidScroll(_:)","symbol_kind":"source.lang.swift.decl.function.method.instance","warning":"undocumented"},{"file":"/Users/marc/Dropbox/projects/Marvel Heroes/Marvel Heroes/Views/HeroDetailVC.swift","line":123,"symbol":"collectionView(_:cellForItemAtIndexPath:)","symbol_kind":"source.lang.swift.decl.function.method.instance","warning":"undocumented"},{"file":"/Users/marc/Dropbox/projects/Marvel Heroes/Marvel Heroes/Views/HeroDetailVC.swift","line":145,"symbol":"collectionView(_:numberOfItemsInSection:)","symbol_kind":"source.lang.swift.decl.function.method.instance","warning":"undocumented"},{"file":"/Users/marc/Dropbox/projects/Marvel Heroes/Marvel Heroes/Views/HeroDetailVC.swift","line":150,"symbol":"numberOfSectionsInCollectionView(_:)","symbol_kind":"source.lang.swift.decl.function.method.instance","warning":"undocumented"},{"file":"/Users/marc/Dropbox/projects/Marvel Heroes/Marvel Heroes/Views/HeroDetailVC.swift","line":155,"symbol":"popVC()","symbol_kind":"source.lang.swift.decl.function.method.instance","warning":"undocumented"},{"file":"/Users/marc/Dropbox/projects/Marvel Heroes/Marvel Heroes/UIViewExtensions.swift","line":17,"symbol":"fadeIn(_:delay:completion:)","symbol_kind":"source.lang.swift.decl.function.method.instance","warning":"undocumented"},{"file":"/Users/marc/Dropbox/projects/Marvel Heroes/Marvel Heroes/UIViewExtensions.swift","line":22,"symbol":"fadeOut(_:delay:completion:)","symbol_kind":"source.lang.swift.decl.function.method.instance","warning":"undocumented"},{"file":"/Users/marc/Dropbox/projects/Marvel Heroes/Marvel Heroes/Model/Hero.swift","line":17,"symbol":"_name","symbol_kind":"source.lang.swift.decl.var.instance","warning":"undocumented"},{"file":"/Users/marc/Dropbox/projects/Marvel Heroes/Marvel Heroes/Model/Hero.swift","line":18,"symbol":"_heroId","symbol_kind":"source.lang.swift.decl.var.instance","warning":"undocumented"},{"file":"/Users/marc/Dropbox/projects/Marvel Heroes/Marvel Heroes/Model/Hero.swift","line":19,"symbol":"_desc","symbol_kind":"source.lang.swift.decl.var.instance","warning":"undocumented"},{"file":"/Users/marc/Dropbox/projects/Marvel Heroes/Marvel Heroes/Model/Hero.swift","line":20,"symbol":"_modified","symbol_kind":"source.lang.swift.decl.var.instance","warning":"undocumented"},{"file":"/Users/marc/Dropbox/projects/Marvel Heroes/Marvel Heroes/Model/Hero.swift","line":21,"symbol":"_thumbnailUrl","symbol_kind":"source.lang.swift.decl.var.instance","warning":"undocumented"},{"file":"/Users/marc/Dropbox/projects/Marvel Heroes/Marvel Heroes/Model/Hero.swift","line":23,"symbol":"init(name:heroId:desc:modified:thumbnailUrl:)","symbol_kind":"source.lang.swift.decl.function.method.instance","warning":"undocumented"},{"file":"/Users/marc/Dropbox/projects/Marvel Heroes/Marvel Heroes/Model/Hero.swift","line":31,"symbol":"name","symbol_kind":"source.lang.swift.decl.var.instance","warning":"undocumented"},{"file":"/Users/marc/Dropbox/projects/Marvel Heroes/Marvel Heroes/Model/Hero.swift","line":35,"symbol":"heroId","symbol_kind":"source.lang.swift.decl.var.instance","warning":"undocumented"},{"file":"/Users/marc/Dropbox/projects/Marvel Heroes/Marvel Heroes/Model/Hero.swift","line":39,"symbol":"desc","symbol_kind":"source.lang.swift.decl.var.instance","warning":"undocumented"},{"file":"/Users/marc/Dropbox/projects/Marvel Heroes/Marvel Heroes/Model/Hero.swift","line":48,"symbol":"thumbnailUrl","symbol_kind":"source.lang.swift.decl.var.instance","warning":"undocumented"},{"file":"/Users/marc/Dropbox/projects/Marvel Heroes/Marvel Heroes/Model/Hero.swift","line":55,"symbol":"description","symbol_kind":"source.lang.swift.decl.var.instance","warning":"undocumented"},{"file":"/Users/marc/Dropbox/projects/Marvel Heroes/Marvel Heroes/Controllers/MasterViewController.swift","line":18,"symbol":"collection","symbol_kind":"source.lang.swift.decl.var.instance","warning":"undocumented"},{"file":"/Users/marc/Dropbox/projects/Marvel Heroes/Marvel Heroes/Controllers/MasterViewController.swift","line":19,"symbol":"searchBar","symbol_kind":"source.lang.swift.decl.var.instance","warning":"undocumented"},{"file":"/Users/marc/Dropbox/projects/Marvel Heroes/Marvel Heroes/Controllers/MasterViewController.swift","line":20,"symbol":"searchController","symbol_kind":"source.lang.swift.decl.var.instance","warning":"undocumented"},{"file":"/Users/marc/Dropbox/projects/Marvel Heroes/Marvel Heroes/Controllers/MasterViewController.swift","line":22,"symbol":"heroes","symbol_kind":"source.lang.swift.decl.var.instance","warning":"undocumented"},{"file":"/Users/marc/Dropbox/projects/Marvel Heroes/Marvel Heroes/Controllers/MasterViewController.swift","line":23,"symbol":"filteredHeroes","symbol_kind":"source.lang.swift.decl.var.instance","warning":"undocumented"},{"file":"/Users/marc/Dropbox/projects/Marvel Heroes/Marvel Heroes/Controllers/MasterViewController.swift","line":24,"symbol":"inSearchMode","symbol_kind":"source.lang.swift.decl.var.instance","warning":"undocumented"},{"file":"/Users/marc/Dropbox/projects/Marvel Heroes/Marvel Heroes/Controllers/MasterViewController.swift","line":25,"symbol":"currentOffset","symbol_kind":"source.lang.swift.decl.var.instance","warning":"undocumented"},{"file":"/Users/marc/Dropbox/projects/Marvel Heroes/Marvel Heroes/Controllers/MasterViewController.swift","line":27,"symbol":"viewDidLoad()","symbol_kind":"source.lang.swift.decl.function.method.instance","warning":"undocumented"},{"file":"/Users/marc/Dropbox/projects/Marvel Heroes/Marvel Heroes/Controllers/MasterViewController.swift","line":50,"symbol":"deinit","symbol_kind":"source.lang.swift.decl.function.method.instance","warning":"undocumented"},{"file":"/Users/marc/Dropbox/projects/Marvel Heroes/Marvel Heroes/Controllers/MasterViewController.swift","line":55,"symbol":"listenToNotifications()","symbol_kind":"source.lang.swift.decl.function.method.instance","warning":"undocumented"},{"file":"/Users/marc/Dropbox/projects/Marvel Heroes/Marvel Heroes/Controllers/MasterViewController.swift","line":73,"symbol":"viewWillAppear(_:)","symbol_kind":"source.lang.swift.decl.function.method.instance","warning":"undocumented"},{"file":"/Users/marc/Dropbox/projects/Marvel Heroes/Marvel Heroes/Controllers/MasterViewController.swift","line":80,"symbol":"configureSearchController()","symbol_kind":"source.lang.swift.decl.function.method.instance","warning":"undocumented"},{"file":"/Users/marc/Dropbox/projects/Marvel Heroes/Marvel Heroes/Controllers/MasterViewController.swift","line":96,"symbol":"searchBarSearchButtonClicked(_:)","symbol_kind":"source.lang.swift.decl.function.method.instance","warning":"undocumented"},{"file":"/Users/marc/Dropbox/projects/Marvel Heroes/Marvel Heroes/Controllers/MasterViewController.swift","line":100,"symbol":"searchBar(_:textDidChange:)","symbol_kind":"source.lang.swift.decl.function.method.instance","warning":"undocumented"},{"file":"/Users/marc/Dropbox/projects/Marvel Heroes/Marvel Heroes/Controllers/MasterViewController.swift","line":115,"symbol":"updateSearchResultsForSearchController(_:)","symbol_kind":"source.lang.swift.decl.function.method.instance","warning":"undocumented"},{"file":"/Users/marc/Dropbox/projects/Marvel Heroes/Marvel Heroes/Controllers/MasterViewController.swift","line":121,"symbol":"searchBarCancelButtonClicked(_:)","symbol_kind":"source.lang.swift.decl.function.method.instance","warning":"undocumented"},{"file":"/Users/marc/Dropbox/projects/Marvel Heroes/Marvel Heroes/Controllers/MasterViewController.swift","line":127,"symbol":"searchBarTextDidEndEditing(_:)","symbol_kind":"source.lang.swift.decl.function.method.instance","warning":"undocumented"},{"file":"/Users/marc/Dropbox/projects/Marvel Heroes/Marvel Heroes/Controllers/MasterViewController.swift","line":135,"symbol":"collectionView(_:cellForItemAtIndexPath:)","symbol_kind":"source.lang.swift.decl.function.method.instance","warning":"undocumented"},{"file":"/Users/marc/Dropbox/projects/Marvel Heroes/Marvel Heroes/Controllers/MasterViewController.swift","line":162,"symbol":"collectionView(_:numberOfItemsInSection:)","symbol_kind":"source.lang.swift.decl.function.method.instance","warning":"undocumented"},{"file":"/Users/marc/Dropbox/projects/Marvel Heroes/Marvel Heroes/Controllers/MasterViewController.swift","line":172,"symbol":"numberOfSectionsInCollectionView(_:)","symbol_kind":"source.lang.swift.decl.function.method.instance","warning":"undocumented"},{"file":"/Users/marc/Dropbox/projects/Marvel Heroes/Marvel Heroes/Controllers/MasterViewController.swift","line":176,"symbol":"collectionView(_:layout:sizeForItemAtIndexPath:)","symbol_kind":"source.lang.swift.decl.function.method.instance","warning":"undocumented"},{"file":"/Users/marc/Dropbox/projects/Marvel Heroes/Marvel Heroes/Controllers/MasterViewController.swift","line":184,"symbol":"collectionView(_:didSelectItemAtIndexPath:)","symbol_kind":"source.lang.swift.decl.function.method.instance","warning":"undocumented"},{"file":"/Users/marc/Dropbox/projects/Marvel Heroes/Marvel Heroes/Controllers/MasterViewController.swift","line":200,"symbol":"prepareForSegue(_:sender:)","symbol_kind":"source.lang.swift.decl.function.method.instance","warning":"undocumented"},{"file":"/Users/marc/Dropbox/projects/Marvel Heroes/Marvel Heroes/AppDelegate.swift","line":12,"symbol":"AppDelegate","symbol_kind":"source.lang.swift.decl.class","warning":"undocumented"},{"file":"/Users/marc/Dropbox/projects/Marvel Heroes/Marvel Heroes/AppDelegate.swift","line":14,"symbol":"window","symbol_kind":"source.lang.swift.decl.var.instance","warning":"undocumented"},{"file":"/Users/marc/Dropbox/projects/Marvel Heroes/Marvel Heroes/AppDelegate.swift","line":17,"symbol":"application(_:didFinishLaunchingWithOptions:)","symbol_kind":"source.lang.swift.decl.function.method.instance","warning":"undocumented"},{"file":"/Users/marc/Dropbox/projects/Marvel Heroes/Marvel Heroes/AppDelegate.swift","line":29,"symbol":"applicationWillResignActive(_:)","symbol_kind":"source.lang.swift.decl.function.method.instance","warning":"undocumented"},{"file":"/Users/marc/Dropbox/projects/Marvel Heroes/Marvel Heroes/AppDelegate.swift","line":34,"symbol":"applicationDidEnterBackground(_:)","symbol_kind":"source.lang.swift.decl.function.method.instance","warning":"undocumented"},{"file":"/Users/marc/Dropbox/projects/Marvel Heroes/Marvel Heroes/AppDelegate.swift","line":39,"symbol":"applicationWillEnterForeground(_:)","symbol_kind":"source.lang.swift.decl.function.method.instance","warning":"undocumented"},{"file":"/Users/marc/Dropbox/projects/Marvel Heroes/Marvel Heroes/AppDelegate.swift","line":43,"symbol":"applicationDidBecomeActive(_:)","symbol_kind":"source.lang.swift.decl.function.method.instance","warning":"undocumented"},{"file":"/Users/marc/Dropbox/projects/Marvel Heroes/Marvel Heroes/AppDelegate.swift","line":47,"symbol":"applicationWillTerminate(_:)","symbol_kind":"source.lang.swift.decl.function.method.instance","warning":"undocumented"},{"file":"/Users/marc/Dropbox/projects/Marvel Heroes/Marvel Heroes/Helpers/Constants.swift","line":26,"symbol":"URL_BASE","symbol_kind":"source.lang.swift.decl.var.global","warning":"undocumented"},{"file":"/Users/marc/Dropbox/projects/Marvel Heroes/Marvel Heroes/Helpers/Constants.swift","line":27,"symbol":"URL_CHARACTERS","symbol_kind":"source.lang.swift.decl.var.global","warning":"undocumented"},{"file":"/Users/marc/Dropbox/projects/Marvel Heroes/Marvel Heroes/Helpers/Constants.swift","line":28,"symbol":"URL_COMICS","symbol_kind":"source.lang.swift.decl.var.global","warning":"undocumented"},{"file":"/Users/marc/Dropbox/projects/Marvel Heroes/Marvel Heroes/Helpers/Constants.swift","line":29,"symbol":"URL_CREDENTIALS","symbol_kind":"source.lang.swift.decl.var.global","warning":"undocumented"},{"file":"/Users/marc/Dropbox/projects/Marvel Heroes/Marvel Heroes/Helpers/Constants.swift","line":32,"symbol":"HERO_CELL","symbol_kind":"source.lang.swift.decl.var.global","warning":"undocumented"},{"file":"/Users/marc/Dropbox/projects/Marvel Heroes/Marvel Heroes/Helpers/Constants.swift","line":33,"symbol":"SEGUE_TO_HERO_DETAIL_VC","symbol_kind":"source.lang.swift.decl.var.global","warning":"undocumented"},{"file":"/Users/marc/Dropbox/projects/Marvel Heroes/Marvel Heroes/Helpers/Constants.swift","line":36,"symbol":"SUGGESTION_CELL","symbol_kind":"source.lang.swift.decl.var.global","warning":"undocumented"},{"file":"/Users/marc/Dropbox/projects/Marvel Heroes/Marvel Heroes/Helpers/Constants.swift","line":39,"symbol":"COMIC_CELL","symbol_kind":"source.lang.swift.decl.var.global","warning":"undocumented"},{"file":"/Users/marc/Dropbox/projects/Marvel Heroes/Marvel Heroes/Helpers/Constants.swift","line":40,"symbol":"NO_DESCRIPTION_AVAILABLE_COPY","symbol_kind":"source.lang.swift.decl.var.global","warning":"undocumented"},{"file":"/Users/marc/Dropbox/projects/Marvel Heroes/Marvel Heroes/Helpers/Constants.swift","line":43,"symbol":"NOTIFICATION_HEROES","symbol_kind":"source.lang.swift.decl.var.global","warning":"undocumented"},{"file":"/Users/marc/Dropbox/projects/Marvel Heroes/Marvel Heroes/Helpers/Constants.swift","line":44,"symbol":"NOTIFICATION_COMICS","symbol_kind":"source.lang.swift.decl.var.global","warning":"undocumented"},{"file":"/Users/marc/Dropbox/projects/Marvel Heroes/Marvel Heroes/Helpers/Constants.swift","line":45,"symbol":"NOTIFICATION_SUGGESTIONS","symbol_kind":"source.lang.swift.decl.var.global","warning":"undocumented"},{"file":"/Users/marc/Dropbox/projects/Marvel Heroes/Marvel Heroes/Services/persistencyManager.swift","line":19,"symbol":"heroes","symbol_kind":"source.lang.swift.decl.var.instance","warning":"undocumented"},{"file":"/Users/marc/Dropbox/projects/Marvel Heroes/Marvel Heroes/Services/persistencyManager.swift","line":20,"symbol":"suggestions","symbol_kind":"source.lang.swift.decl.var.instance","warning":"undocumented"},{"file":"/Users/marc/Dropbox/projects/Marvel Heroes/Marvel Heroes/Services/persistencyManager.swift","line":21,"symbol":"comics","symbol_kind":"source.lang.swift.decl.var.instance","warning":"undocumented"},{"file":"/Users/marc/Dropbox/projects/Marvel Heroes/Marvel Heroes/Services/persistencyManager.swift","line":22,"symbol":"cache","symbol_kind":"source.lang.swift.decl.var.instance","warning":"undocumented"},{"file":"/Users/marc/Dropbox/projects/Marvel Heroes/Marvel Heroes/Services/persistencyManager.swift","line":24,"symbol":"init()","symbol_kind":"source.lang.swift.decl.function.method.instance","warning":"undocumented"},{"file":"/Users/marc/Dropbox/projects/Marvel Heroes/Marvel Heroes/Services/persistencyManager.swift","line":78,"symbol":"fetchHeroes()","symbol_kind":"source.lang.swift.decl.function.method.instance","warning":"undocumented"},{"file":"/Users/marc/Dropbox/projects/Marvel Heroes/Marvel Heroes/Services/persistencyManager.swift","line":83,"symbol":"getHeroes()","symbol_kind":"source.lang.swift.decl.function.method.instance","warning":"undocumented"},{"file":"/Users/marc/Dropbox/projects/Marvel Heroes/Marvel Heroes/Services/persistencyManager.swift","line":87,"symbol":"getMoreHeroes(_:)","symbol_kind":"source.lang.swift.decl.function.method.instance","warning":"undocumented"},{"file":"/Users/marc/Dropbox/projects/Marvel Heroes/Marvel Heroes/Services/persistencyManager.swift","line":104,"symbol":"getHeroSuggestions()","symbol_kind":"source.lang.swift.decl.function.method.instance","warning":"undocumented"},{"file":"/Users/marc/Dropbox/projects/Marvel Heroes/Marvel Heroes/Services/persistencyManager.swift","line":108,"symbol":"resetHeroSuggestions()","symbol_kind":"source.lang.swift.decl.function.method.instance","warning":"undocumented"},{"file":"/Users/marc/Dropbox/projects/Marvel Heroes/Marvel Heroes/Services/persistencyManager.swift","line":127,"symbol":"getComics()","symbol_kind":"source.lang.swift.decl.function.method.instance","warning":"undocumented"},{"file":"/Users/marc/Dropbox/projects/Marvel Heroes/Marvel Heroes/Services/persistencyManager.swift","line":136,"symbol":"strokeSanitizer(_:)","symbol_kind":"source.lang.swift.decl.function.method.instance","warning":"undocumented"}],"source_directory":"/Users/marc/Dropbox/projects/Marvel Heroes"}